MiModD/.__first_run__
MiModD/.cfg
MiModD/__first_run__.py
MiModD/__init__.py
MiModD/__main__.py
MiModD/anno_weblinks.py
MiModD/auxparsers.py
MiModD/bioobj_base.py
MiModD/cfg.py
MiModD/cloudmap.py
MiModD/config.py
MiModD/convert.py
MiModD/converters.py
MiModD/decox.py
MiModD/deletion_calling.py
MiModD/dialogs.py
MiModD/enablegalaxy.py
MiModD/encoding_base.py
MiModD/fasta.py
MiModD/fileinfo.py
MiModD/help.py
MiModD/index.py
MiModD/intervaltree.py
MiModD/iterx.py
MiModD/liftover.py
MiModD/plotters.py
MiModD/pybcftools.py
MiModD/pysamtools.py
MiModD/pyvcf.py
MiModD/rebase.py
MiModD/samheader.py
MiModD/sanitize.py
MiModD/snap.py
MiModD/stats_base.py
MiModD/templates.py
MiModD/tmpfiles.py
MiModD/upgrade.py
MiModD/variant_annotation.py
MiModD/variant_calling.py
MiModD/vcf_filter.py
MiModD/bin/bcftools
MiModD/bin/mimodd
MiModD/bin/samtools
MiModD/bin/snap
MiModD/galaxy_data/mimodd_tool_conf.xml
MiModD/galaxy_data/mimodd/annotate_variants.xml
MiModD/galaxy_data/mimodd/bamsort.xml
MiModD/galaxy_data/mimodd/cloudmap.xml
MiModD/galaxy_data/mimodd/convert.xml
MiModD/galaxy_data/mimodd/covstats.xml
MiModD/galaxy_data/mimodd/deletion_predictor.xml
MiModD/galaxy_data/mimodd/fileinfo.xml
MiModD/galaxy_data/mimodd/macros.xml
MiModD/galaxy_data/mimodd/rebase.xml
MiModD/galaxy_data/mimodd/reheader.xml
MiModD/galaxy_data/mimodd/sam_header.xml
MiModD/galaxy_data/mimodd/snap_caller.xml
MiModD/galaxy_data/mimodd/snp_caller_caller.xml
MiModD/galaxy_data/mimodd/snpeff_genomes.xml
MiModD/galaxy_data/mimodd/varextract.xml
MiModD/galaxy_data/mimodd/varreport.xml
MiModD/galaxy_data/mimodd/vcf_filter.xml
MiModD/galaxy_data/mimodd/test-data/a.bam
MiModD/galaxy_data/mimodd/test-data/a.bcf
MiModD/galaxy_data/mimodd/test-data/a.fa
MiModD/galaxy_data/mimodd/test-data/a.sam
MiModD/galaxy_data/mimodd/test-data/a.vcf
MiModD/galaxy_data/mimodd/test-data/a_part1.bam
MiModD/galaxy_data/mimodd/test-data/a_part2.bam
MiModD/install_utils/setuptools-22.0.0.dist-info/DESCRIPTION.rst
MiModD/install_utils/setuptools-22.0.0.dist-info/INSTALLER
MiModD/install_utils/setuptools-22.0.0.dist-info/METADATA
MiModD/install_utils/setuptools-22.0.0.dist-info/RECORD
MiModD/install_utils/setuptools-22.0.0.dist-info/WHEEL
MiModD/install_utils/setuptools-22.0.0.dist-info/dependency_links.txt
MiModD/install_utils/setuptools-22.0.0.dist-info/entry_points.txt
MiModD/install_utils/setuptools-22.0.0.dist-info/metadata.json
MiModD/install_utils/setuptools-22.0.0.dist-info/top_level.txt
MiModD/install_utils/setuptools-22.0.0.dist-info/zip-safe
MiModD-0.1.9.dist-info/DESCRIPTION.rst
MiModD-0.1.9.dist-info/METADATA
MiModD-0.1.9.dist-info/RECORD
MiModD-0.1.9.dist-info/WHEEL
MiModD-0.1.9.dist-info/metadata.json
MiModD-0.1.9.dist-info/top_level.txt
